gbdm/__init__.py
gbdm/__main__.py
gbdm/main.py
git_utils_dmaahs2017-0.0.5.dist-info/LICENSE
git_utils_dmaahs2017-0.0.5.dist-info/METADATA
git_utils_dmaahs2017-0.0.5.dist-info/WHEEL
git_utils_dmaahs2017-0.0.5.dist-info/top_level.txt
git_utils_dmaahs2017-0.0.5.dist-info/RECORD
