Metadata-Version: 2.1
Name: git-utils-dmaahs2017
Version: 0.0.5
Summary: Additional utils for git
Home-page: https://github.com/dmaahs2017/git-utils
Author: Dalton Maahs
Author-email: maahs2017@gmail.com
License: UNKNOWN
Platform: UNKNOWN
Classifier: Programming Language :: Python :: 3.6
Classifier: License :: OSI Approved :: MIT License
Classifier: Operating System :: OS Independent
Requires-Python: >=3.6
Requires-Dist: GitPython
Requires-Dist: PyInquirer
